README.md
setup.py
rsdf/__init__.py
rsdf/redshift.py
rsdf/s3.py
rsdf.egg-info/PKG-INFO
rsdf.egg-info/SOURCES.txt
rsdf.egg-info/dependency_links.txt
rsdf.egg-info/requires.txt
rsdf.egg-info/top_level.txt